_seidel.cpython-35m-i386-linux-gnu.so
seidel/x_node.py
seidel/trapezoidal_map.py
seidel/y_node.py
seidel/trapezoid.py
seidel/bounding_box.py
seidel/node.py
seidel/hints.py
seidel/point.py
seidel/edge.py
seidel/__init__.py
seidel/leaf.py
seidel-0.0.2.dist-info/top_level.txt
seidel-0.0.2.dist-info/RECORD
seidel-0.0.2.dist-info/METADATA
seidel-0.0.2.dist-info/LICENSE
seidel-0.0.2.dist-info/WHEEL
