Metadata-Version: 2.1
Name: seidel
Version: 0.0.2
Summary: Randomized algorithm for trapezoidal decomposition by R. Seidel.
Home-page: https://github.com/lycantropos/seidel/
Author: Azat Ibrakov
Author-email: azatibrakov@gmail.com
License: MIT License
Download-URL: https://github.com/lycantropos/seidel/archive/master.zip
Platform: UNKNOWN
Classifier: License :: OSI Approved :: MIT License
Classifier: Programming Language :: Python :: 3.5
Classifier: Programming Language :: Python :: 3.6
Classifier: Programming Language :: Python :: 3.7
Classifier: Programming Language :: Python :: 3.8
Classifier: Programming Language :: Python :: Implementation :: CPython
Requires-Python: >=3.5
Requires-Dist: pybind11 (>=2.5.0)
Requires-Dist: reprit (>=0.2.2)
